gsdbs/dbclient.py
gsdbs/gsfilter.py
gsdbs/gsmessenger.py
gsdbs/missioncontrol.py
gsdbs/utils.py
gs_dbs_client-0.2.6.post42.dist-info/METADATA
gs_dbs_client-0.2.6.post42.dist-info/WHEEL
gs_dbs_client-0.2.6.post42.dist-info/entry_points.txt
gs_dbs_client-0.2.6.post42.dist-info/top_level.txt
gs_dbs_client-0.2.6.post42.dist-info/RECORD
