Metadata-Version: 2.1
Name: gs-dbs-client
Version: 0.2.6.post42
Summary: python wrapper for the Glass Sphere DBS
Home-page: https://glass-sphere-ai.de
Author: Glass Sphere Software
Author-email: 
License: MIT
Platform: UNKNOWN
Classifier: License :: OSI Approved :: MIT License
Classifier: Programming Language :: Python :: 3
Classifier: Programming Language :: Python :: 3.7
Requires-Dist: gql
Requires-Dist: pandas
Requires-Dist: Twisted
Requires-Dist: ujson
Requires-Dist: PyYAML
Requires-Dist: requests
Requires-Dist: aiohttp
Requires-Dist: stomper
Requires-Dist: graphql-core
Requires-Dist: Pillow
Requires-Dist: websocket-client
Requires-Dist: protobuf (>=3.3.0)
Requires-Dist: requests-toolbelt
Requires-Dist: ffmpeg-python
Requires-Dist: asyncio
